rure/regex.py
rure/lib.py
rure/_native.py
rure/__init__.py
rure/_native__ffi.py
rure/exceptions.py
rure/decorators.py
rure/_native__lib.so
rure/tests/test_rure.py
rure/tests/test_rureset.py
rure/tests/test_matchobject.py
rure/tests/__init__.py
rure/tests/test_regexobject.py
rure-0.2.2.dist-info/RECORD
rure-0.2.2.dist-info/top_level.txt
rure-0.2.2.dist-info/WHEEL
rure-0.2.2.dist-info/METADATA
