Metadata-Version: 2.1
Name: rure
Version: 0.2.2
Summary: Python bindings for the Rust `regex` crate. This implementation uses finite automata and guarantees linear time matching on all inputs.
Home-page: https://github.com/davidblewett/rure-python
Author: David Blewett
Author-email: david@dawninglight.net
License: MIT
Keywords: regex,rust,dfa,automata,data_structures
Platform: UNKNOWN
Classifier: Development Status :: 4 - Beta
Classifier: Intended Audience :: Developers
Classifier: License :: OSI Approved :: MIT License
Classifier: Programming Language :: Python :: 2.7
Classifier: Programming Language :: Python :: 3.6
Classifier: Programming Language :: Python :: 3.7
Classifier: Programming Language :: Python :: 3.8
Classifier: Topic :: Text Processing :: Indexing
Requires-Dist: milksnake
Requires-Dist: cffi (>=1.5.0)
Requires-Dist: six
